[
  {
    "seq": "1",
    "first": "Elmer",
    "last": "Barber",
    "age": "26",
    "department": "sociology",
    "level": "level 16",
    "date employed": "January 16 2001",
    "special assignment": "course advisor sociology 200lvl",
    "email": "blossmbabalola@gmail.com",
    "phone number": "09084458324",
    "highest level of education": "Phd"
  },
  {
    "seq": "2",
    "first": "Cecilia",
    "last": "Sherman",
    "age": "27",
    "department": "accounting",
    "level": "level 16",
    "date employed": "February 16 1998",
    "special assignment": "course advisor accounting 300lvl",
    "email": "blossybab70@gmail.com",
    "phone number": "09084458324",
    "highest level of education": "Msc"
  },
  {
    "seq": "3",
    "first": "Franklin",
    "last": "Wilkins",
    "age": "34",
    "department": "applied physics",
    "level": "level 16",
    "date employed": "April 16 2003",
    "special assignment": "course advisor applied physics 100lvl",
    "email": "saphashb@gmail.com",
    "phone number": "09084458324",
    "highest level of education": "Phd"
  },
  {
    "seq": "4",
    "first": "Flora",
    "last": "Benson",
    "age": "49",
    "department": "applied mathematics",
    "level": "level 16",
    "date employed": "August 4 1995",
    "special assignment": "course advisor applied mathematics 400lvl",
    "email": "blossom@themullingsgroup.com",
    "phone number": "09084458324",
    "highest level of education": "Phd"
  },
  {
    "seq": "5",
    "first": "Eunice",
    "last": "Cole",
    "age": "36",
    "department": "architecture",
    "level": "level 16",
    "date employed": "December 31 2003",
    "special assignment": "course advisor architecture 300lvl",
    "email": "lenut@dejlizi.ls",
    "phone number": "09084458324",
    "highest level of education": "Bsc"
  },
  {
    "seq": "6",
    "first": "Mayme",
    "last": "Norton",
    "age": "41",
    "department": "biochemistry",
    "level": "level 16",
    "date employed": "April 16 1985",
    "special assignment": "course advisor biochemistry 500lvl",
    "email": "korta@pohuga.td",
    "phone number": "09084458324",
    "highest level of education": "highest level of education"
  },
  {
    "seq": "7",
    "first": "Winifred",
    "last": "Cortez",
    "age": "51",
    "department": "biology",
    "level": "level 16",
    "date employed": "March 20 2004",
    "special assignment": "course advisor biology 200lvl",
    "email": "onoheher@jigco.tv",
    "phone number": "09084458324",
    "highest level of education": "Phd"
  },
  {
    "seq": "8",
    "first": "Nelle",
    "last": "Ford",
    "age": "35",
    "department": "chemical engineering",
    "level": "level 16",
    "date employed": "November 15 2010",
    "special assignment": "course advisor chemical engineering 100lvl",
    "email": "ewu@dagfini.cw",
    "phone number": "09084458324",
    "highest level of education": "Doctorate"
  },
  {
    "seq": "9",
    "first": "Lester",
    "last": "Lamb",
    "age": "62",
    "department": "civil engineering",
    "level": "level 16",
    "date employed": "January 16 2004",
    "special assignment": "course advisor civil engineering 200lvl",
    "email": "mija@tetfe.de",
    "phone number": "09084458324",
    "highest level of education": "Msc"
  },
  {
    "seq": "10",
    "first": "Lillian",
    "last": "Reed",
    "age": "53",
    "department": "economics",
    "level": "level 16",
    "date employed": "February 1 20015",
    "special assignment": "course advisor economics 500lvl",
    "email": "siwac@loike.fo",
    "phone number": "09084458324",
    "highest level of education": "Phd"
  }
]